setup.cfg
setup.py
zab_rev/__init__.py
zab_rev/send_zabbix.py
zab_rev.egg-info/PKG-INFO
zab_rev.egg-info/SOURCES.txt
zab_rev.egg-info/dependency_links.txt
zab_rev.egg-info/not-zip-safe
zab_rev.egg-info/top_level.txt