Metadata-Version: 2.1
Name: zab-rev
Version: 0.0
Summary: Send message to zabbix server
Author-email: sagrityanin4@gmail.com
